FastKAST/FastKAST_annot.py
FastKAST/QuadKAST_annot.py
FastKAST/__init__.py
FastKAST/estimators.py
FastKAST/fastmle_res_jax.py
FastKAST/utils.py
fast_kernel_set_test-0.1.1.dist-info/METADATA
fast_kernel_set_test-0.1.1.dist-info/WHEEL
fast_kernel_set_test-0.1.1.dist-info/top_level.txt
fast_kernel_set_test-0.1.1.dist-info/RECORD
