Metadata-Version: 2.1
Name: fast-kernel-set-test
Version: 0.1.1
Summary: This is the package for various epistasis related softwares.
Home-page: https://github.com/sriramlab/FastKAST
Author: Boyang Fu
Author-email: fbyang1995@gmail.com
License: UNKNOWN
Platform: UNKNOWN
Classifier: Programming Language :: Python :: 3
Classifier: License :: OSI Approved :: MIT License
Classifier: Operating System :: OS Independent
Requires-Python: >=3.6
Requires-Dist: pandas-plink==2.1.0
Requires-Dist: chi2comb
Requires-Dist: julia
Requires-Dist: bed-reader
Requires-Dist: threadpoolctl
Requires-Dist: numba
Requires-Dist: fastlmmclib
